setup.py
larkClient/__init__.py
lark_client.egg-info/PKG-INFO
lark_client.egg-info/SOURCES.txt
lark_client.egg-info/dependency_links.txt
lark_client.egg-info/requires.txt
lark_client.egg-info/top_level.txt