Metadata-Version: 1.2
Name: lark-client
Version: 1.2.1
Summary: 飞书OpenAPI的客户端
Home-page: UNKNOWN
Author: 刘星辰
Author-email: tbyes@foxmail.com
License: MIT Licence
Keywords: lark,飞书,feishu
Platform: any
Requires-Python: >=3.6
